odoo/addons/sale_payment_term_security/README.rst
odoo/addons/sale_payment_term_security/__init__.py
odoo/addons/sale_payment_term_security/__manifest__.py
odoo/addons/sale_payment_term_security/i18n/es.po
odoo/addons/sale_payment_term_security/i18n/sale_payment_term_security.pot
odoo/addons/sale_payment_term_security/models/__init__.py
odoo/addons/sale_payment_term_security/models/sale_order.py
odoo/addons/sale_payment_term_security/readme/CONFIGURE.rst
odoo/addons/sale_payment_term_security/readme/CONTRIBUTORS.rst
odoo/addons/sale_payment_term_security/readme/DESCRIPTION.rst
odoo/addons/sale_payment_term_security/static/description/icon.png
odoo/addons/sale_payment_term_security/static/description/index.html
odoo/addons/sale_payment_term_security/tests/__init__.py
odoo/addons/sale_payment_term_security/tests/test_sale_payment_term_security.py
odoo13_addon_sale_payment_term_security-13.0.1.0.1.dev4.dist-info/METADATA
odoo13_addon_sale_payment_term_security-13.0.1.0.1.dev4.dist-info/WHEEL
odoo13_addon_sale_payment_term_security-13.0.1.0.1.dev4.dist-info/top_level.txt
odoo13_addon_sale_payment_term_security-13.0.1.0.1.dev4.dist-info/RECORD
